ckanext_dcat-2.4.2-py3.9-nspkg.pth
ckanext/dcat/__init__.py
ckanext/dcat/blueprints.py
ckanext/dcat/cli.py
ckanext/dcat/config_declaration.yml
ckanext/dcat/config_declaration_croissant.yml
ckanext/dcat/config_declaration_structured_data.yml
ckanext/dcat/controllers.py
ckanext/dcat/converters.py
ckanext/dcat/exceptions.py
ckanext/dcat/helpers.py
ckanext/dcat/interfaces.py
ckanext/dcat/logic.py
ckanext/dcat/processors.py
ckanext/dcat/utils.py
ckanext/dcat/validators.py
ckanext/dcat/harvesters/__init__.py
ckanext/dcat/harvesters/_json.py
ckanext/dcat/harvesters/base.py
ckanext/dcat/harvesters/rdf.py
ckanext/dcat/harvesters/xml.py
ckanext/dcat/i18n/ckanext-dcat.pot
ckanext/dcat/i18n/ca/LC_MESSAGES/ckanext-dcat.mo
ckanext/dcat/i18n/ca/LC_MESSAGES/ckanext-dcat.po
ckanext/dcat/i18n/es/LC_MESSAGES/ckanext-dcat.mo
ckanext/dcat/i18n/es/LC_MESSAGES/ckanext-dcat.po
ckanext/dcat/plugins/__init__.py
ckanext/dcat/profiles/__init__.py
ckanext/dcat/profiles/base.py
ckanext/dcat/profiles/croissant.py
ckanext/dcat/profiles/dcat_us_3.py
ckanext/dcat/profiles/euro_dcat_ap.py
ckanext/dcat/profiles/euro_dcat_ap_2.py
ckanext/dcat/profiles/euro_dcat_ap_3.py
ckanext/dcat/profiles/euro_dcat_ap_base.py
ckanext/dcat/profiles/euro_dcat_ap_scheming.py
ckanext/dcat/profiles/euro_health_dcat_ap.py
ckanext/dcat/profiles/schemaorg.py
ckanext/dcat/schemas/__init__.py
ckanext/dcat/schemas/croissant.yaml
ckanext/dcat/schemas/dcat_ap_dataset_series.yaml
ckanext/dcat/schemas/dcat_ap_full.yaml
ckanext/dcat/schemas/dcat_ap_in_series.yaml
ckanext/dcat/schemas/dcat_ap_multilingual.yaml
ckanext/dcat/schemas/dcat_ap_recommended.yaml
ckanext/dcat/schemas/dcat_us_full.yaml
ckanext/dcat/schemas/dcat_us_recommended.yaml
ckanext/dcat/schemas/health_dcat_ap.yaml
ckanext/dcat/schemas/health_dcat_ap_multilingual.yaml
ckanext/dcat/schemas/presets.yaml
ckanext/dcat/schemas/publisher_organization.yaml
ckanext/dcat/templates/croissant/package/read_base.html
ckanext/dcat/templates/dcat/home/index.html
ckanext_dcat-2.4.2.dist-info/METADATA
ckanext_dcat-2.4.2.dist-info/WHEEL
ckanext_dcat-2.4.2.dist-info/entry_points.txt
ckanext_dcat-2.4.2.dist-info/namespace_packages.txt
ckanext_dcat-2.4.2.dist-info/top_level.txt
ckanext_dcat-2.4.2.dist-info/RECORD
