Metadata-Version: 2.4
Name: ckanext-dcat
Version: 2.4.2
Summary: Plugins for exposing and consuming DCAT metadata on CKAN
Author-email: Adrià Mercader <amercadero@gmail.com>
Maintainer: Seitenbau Govdata, Stefan Oderbolz
Maintainer-email: CKAN Tech Team and contributors <tech-team@ckan.org>
License: AGPL
Project-URL: Documentation, https://docs.ckan.org/projects/ckanext-dcat
Project-URL: Repository, https://github.com/ckan/ckanext-dcat
Project-URL: Issues, https://github.com/ckan/ckanext-dcat/issues
Project-URL: Changelog, https://docs.ckan.org/projects/ckanext-dcat/en/latest/changelog/
Keywords: ckan,ckanext,DCAT,DCAT-AP,Schema.org,Croissant ML,Linked data,RDF,Semantic data
Classifier: Intended Audience :: Developers
Classifier: Development Status :: 5 - Production/Stable
Classifier: License :: OSI Approved :: GNU Affero General Public License v3
Classifier: Programming Language :: Python :: 3.8
Classifier: Programming Language :: Python :: 3.9
Classifier: Programming Language :: Python :: 3.10
Classifier: Programming Language :: Python :: 3.11
Classifier: Programming Language :: Python :: 3.12
Requires-Dist: rdflib>=6.1.1
Requires-Dist: pyld>=2.0.4
Requires-Dist: geomet>=0.2.0
Requires-Dist: ckantoolkit>=0.0.7
Provides-Extra: dev
Requires-Dist: responses>=0.25.2; extra == "dev"
Requires-Dist: pyshacl; extra == "dev"
Requires-Dist: mlcroissant==1.0.21; python_version >= "3.10" and extra == "dev"
Requires-Dist: mock; extra == "dev"
Requires-Dist: pytest-ckan; extra == "dev"
Requires-Dist: pytest-cov; extra == "dev"
Requires-Dist: pytest-pretty; extra == "dev"
